dictgen/__init__.py
dictgen/generate.py
dictgen/utils.py
dictgen-0.1.dist-info/LICENSE
dictgen-0.1.dist-info/METADATA
dictgen-0.1.dist-info/WHEEL
dictgen-0.1.dist-info/top_level.txt
dictgen-0.1.dist-info/RECORD
