Metadata-Version: 2.1
Name: dictgen
Version: 0.1
Summary: Customisable random dictionary generator for fuzz testing
Home-page: https://github.com/sg3-141-592/dictgen
Author: Sean @ CompactCloud
Author-email: sean@compactcloud.co.uk
License: MIT
Classifier: Development Status :: 4 - Beta
Classifier: License :: OSI Approved :: MIT License
Classifier: Programming Language :: Python :: 3
Classifier: Topic :: Software Development :: Testing
License-File: LICENSE
